xp_pen/__init__.py
xp_pen-0.1.1.dist-info/METADATA
xp_pen-0.1.1.dist-info/WHEEL
xp_pen-0.1.1.dist-info/RECORD
