Metadata-Version: 2.1
Name: xp-pen
Version: 0.1.1
Summary: 
Author: Todd Sifleet
Author-email: todd.sifleet@gmail.com
Requires-Python: >=3.11,<4.0
Classifier: Programming Language :: Python :: 3
Classifier: Programming Language :: Python :: 3.11
Classifier: Programming Language :: Python :: 3.12
Requires-Dist: pyusb (>=1.2.1,<2.0.0)
